teampulls/__init__.py
teampulls/teampulls.py
teampulls-0.2.6.dist-info/LICENSE
teampulls-0.2.6.dist-info/METADATA
teampulls-0.2.6.dist-info/WHEEL
teampulls-0.2.6.dist-info/entry_points.txt
teampulls-0.2.6.dist-info/top_level.txt
teampulls-0.2.6.dist-info/RECORD
