Metadata-Version: 2.1
Name: teampulls
Version: 0.2.6
Summary: teampulls lists all of the pull requests for a list of users and repositories and highlights the old ones in red.
Home-page: https://github.com/brejoc/teampulls
Author: Jochen Breuer
Author-email: jbreuer@suse.de
Maintainer: Jochen Breuer
Maintainer-email: jbreuer@suse.de
License: GPLv3
Keywords: Github Pull Requests team
Platform: any
Requires-Dist: toml
Requires-Dist: requests
Requires-Dist: python-dateutil
Requires-Dist: docopt
